<PAMDataset>
  <Metadata>
    <MDI key="DataType">Thematic</MDI>
  </Metadata>
  <PAMRasterBand band="1">
    <Histograms>
      <HistItem>
        <HistMin>-0.5</HistMin>
        <HistMax>34.5</HistMax>
        <BucketCount>35</BucketCount>
        <IncludeOutOfRange>1</IncludeOutOfRange>
        <Approximate>0</Approximate>
        <HistCounts>1695459|0|0|0|0|0|0|0|25762|73050|209761|12010|0|2742|0|38245|63918|8131|0|1|347|0|1375|652|0|1151|546|4221|0|2018|0|1630|1089|9111|28371</HistCounts>
      </HistItem>
    </Histograms>
    <Metadata>
      <MDI key="RepresentationType">THEMATIC</MDI>
      <MDI key="STATISTICS_COVARIANCES">41.71108225964242</MDI>
      <MDI key="STATISTICS_EXCLUDEDVALUES"></MDI>
      <MDI key="STATISTICS_MAXIMUM">34</MDI>
      <MDI key="STATISTICS_MEAN">2.9738721502668</MDI>
      <MDI key="STATISTICS_MINIMUM">0</MDI>
      <MDI key="STATISTICS_SKIPFACTORX">1</MDI>
      <MDI key="STATISTICS_SKIPFACTORY">1</MDI>
      <MDI key="STATISTICS_STDDEV">6.4584117443565</MDI>
    </Metadata>
  </PAMRasterBand>
</PAMDataset>
